src/__init__.py
src/ai/__init__.py
src/ai/base.py
src/ai/claude.py
src/ai/openai.py
src/cli/__init__.py
src/cli/main.py
src/core/__init__.py
src/core/diff.py
src/core/editor.py
src/core/file_handler.py
src/ui/__init__.py
src/ui/diff_view.py
src/ui/display.py
src/ui/prompt.py
src/utils/__init__.py
src/utils/config.py
src/utils/syntax.py
cli_edit-0.1.0.dist-info/METADATA
cli_edit-0.1.0.dist-info/WHEEL
cli_edit-0.1.0.dist-info/entry_points.txt
cli_edit-0.1.0.dist-info/top_level.txt
cli_edit-0.1.0.dist-info/RECORD
