Metadata-Version: 2.4
Name: cli-edit
Version: 0.1.0
Summary: AI code editor for terminals
Author-email: Gustav Koser <gustav.koser@gmail.com>
License: MIT
Project-URL: Repository, https://github.com/amgustav/cli-edit
Requires-Python: >=3.11
Requires-Dist: anthropic>=0.18.0
Requires-Dist: openai>=1.0.0
Requires-Dist: click>=8.0.0
Requires-Dist: rich>=13.0.0
Requires-Dist: pydantic>=2.0.0
Requires-Dist: tomli>=2.0.0
Requires-Dist: pygments>=2.0.0
Provides-Extra: dev
Requires-Dist: pytest>=7.0.0; extra == "dev"
Requires-Dist: pytest-cov>=4.0.0; extra == "dev"
Requires-Dist: mypy>=1.0.0; extra == "dev"
Requires-Dist: ruff>=0.1.0; extra == "dev"
